pyantz/__init__.py
pyantz/py.typed
pyantz/run.py
pyantz/infrastructure/__init__.py
pyantz/infrastructure/config/__init__.py
pyantz/infrastructure/config/base.py
pyantz/infrastructure/config/get_functions.py
pyantz/infrastructure/config/local_submitter.py
pyantz/infrastructure/config/submitters/__init__.py
pyantz/infrastructure/config/submitters/slurm_submitter.py
pyantz/infrastructure/core/__init__.py
pyantz/infrastructure/core/job.py
pyantz/infrastructure/core/manager.py
pyantz/infrastructure/core/mutable_job.py
pyantz/infrastructure/core/pipeline.py
pyantz/infrastructure/core/status.py
pyantz/infrastructure/core/submitter_job.py
pyantz/infrastructure/core/variables.py
pyantz/infrastructure/distributed_queue/__init__.py
pyantz/infrastructure/distributed_queue/relational/__init__.py
pyantz/infrastructure/distributed_queue/relational/queue_orm.py
pyantz/infrastructure/distributed_queue/relational/sqlite_queue.py
pyantz/infrastructure/hpc/__init__.py
pyantz/infrastructure/hpc/slurm/__init__.py
pyantz/infrastructure/hpc/slurm/restful/__init__.py
pyantz/infrastructure/hpc/slurm/restful/models/__init__.py
pyantz/infrastructure/hpc/slurm/restful/models/account.py
pyantz/infrastructure/hpc/slurm/restful/models/account_short.py
pyantz/infrastructure/hpc/slurm/restful/models/accounting.py
pyantz/infrastructure/hpc/slurm/restful/models/accounting_allocated.py
pyantz/infrastructure/hpc/slurm/restful/models/accounts_add_cond.py
pyantz/infrastructure/hpc/slurm/restful/models/acct_gather_energy.py
pyantz/infrastructure/hpc/slurm/restful/models/assoc.py
pyantz/infrastructure/hpc/slurm/restful/models/assoc_default.py
pyantz/infrastructure/hpc/slurm/restful/models/assoc_max.py
pyantz/infrastructure/hpc/slurm/restful/models/assoc_max_jobs.py
pyantz/infrastructure/hpc/slurm/restful/models/assoc_max_jobs_per.py
pyantz/infrastructure/hpc/slurm/restful/models/assoc_max_per.py
pyantz/infrastructure/hpc/slurm/restful/models/assoc_max_per_account.py
pyantz-0.1.0.dist-info/METADATA
pyantz-0.1.0.dist-info/WHEEL
pyantz-0.1.0.dist-info/entry_points.txt
pyantz-0.1.0.dist-info/licenses/LICENSE.txt
pyantz-0.1.0.dist-info/RECORD
