Metadata-Version: 2.4
Name: pyantz
Version: 0.1.0
Summary: Add your description here
Author-email: igreen1 <dev@iangreen.dev>
License-File: LICENSE.txt
Requires-Python: >=3.11
Requires-Dist: pydantic>=2.10.6
Requires-Dist: rich>=13.9.4
Requires-Dist: sqlalchemy>=2.0.38
Provides-Extra: pandas
Requires-Dist: pandas>=2.2.3; extra == 'pandas'
Provides-Extra: pyarrow
Requires-Dist: pandas>=2.2.3; extra == 'pyarrow'
Requires-Dist: pyarrow>=19.0.1; extra == 'pyarrow'
Provides-Extra: slurm
Requires-Dist: requests>=2.32.3; extra == 'slurm'
